pixelmagic/__init__.py
pixelmagic/pixelmagic.py
pixelmagic-1.0.dist-info/LICENSE
pixelmagic-1.0.dist-info/METADATA
pixelmagic-1.0.dist-info/WHEEL
pixelmagic-1.0.dist-info/top_level.txt
pixelmagic-1.0.dist-info/RECORD
