Metadata-Version: 2.1
Name: pixelmagic
Version: 1.0
Summary: A package for creating pixelated GIFs from images
Home-page: https://github.com/madhawap/pixelmagic
Author: madhawap
Author-email: madhawa.perera@anu.edu.au
Keywords: pixelated gif imageio pillow
Classifier: Development Status :: 3 - Alpha
Classifier: Intended Audience :: Developers
Classifier: License :: OSI Approved :: MIT License
Classifier: Programming Language :: Python :: 3
Classifier: Programming Language :: Python :: 3.6
Classifier: Programming Language :: Python :: 3.7
Classifier: Programming Language :: Python :: 3.8
Classifier: Programming Language :: Python :: 3.9
Classifier: Programming Language :: Python :: 3.10
License-File: LICENSE
Requires-Dist: imageio
Requires-Dist: Pillow
